diffpssi/optimization_lib/optimizers.py
diffpssi/optimization_lib/ps_optimization.py
diffpssi/power_sim_lib/backend.py
diffpssi/power_sim_lib/load_flow.py
diffpssi/power_sim_lib/simulator.py
diffpssi/power_sim_lib/solvers.py
diffpssi/power_sim_lib/models/blocks.py
diffpssi/power_sim_lib/models/exciters.py
diffpssi/power_sim_lib/models/governors.py
diffpssi/power_sim_lib/models/stabilizers.py
diffpssi/power_sim_lib/models/static_models.py
diffpssi/power_sim_lib/models/synchronous_machine.py
diffpssi-0.0.3.dist-info/LICENSE
diffpssi-0.0.3.dist-info/METADATA
diffpssi-0.0.3.dist-info/WHEEL
diffpssi-0.0.3.dist-info/top_level.txt
diffpssi-0.0.3.dist-info/RECORD
