Metadata-Version: 2.1
Name: diffpssi
Version: 0.0.3
Summary: A differentiable power system simulation tool
Author-email: Georg Kordowich <georg.kordowich@fau.de>
Project-URL: Homepage, https://github.com/georgkordowich/diffpssi
Project-URL: Issues, https://github.com/georgkordowich/diffpssi/issues
Classifier: Programming Language :: Python :: 3
Classifier: License :: OSI Approved :: MIT License
Classifier: Operating System :: OS Independent
Requires-Python: >=3.8
License-File: LICENSE
Requires-Dist: matplotlib
Requires-Dist: numpy
Requires-Dist: torch
Requires-Dist: tqdm
